evince/__init__.py
evince/_version.py
evince/braketview.py
evince/denseview.py
evince/fashionview.py
evince/latticeview.py
evince/mdview.py
evince/morpehusview.py
evince/omoviview.py
evince/pointview.py
evince/spotlight.py
evince/template.py
evince/labextension/package.json
evince/labextension/static/212.0de55918f94a40801c2a.js
evince/labextension/static/212.0de55918f94a40801c2a.js.LICENSE.txt
evince/labextension/static/261.3de77d484f97a9534c44.js
evince/labextension/static/261.ce48b06f655b2ac68f5c.js
evince/labextension/static/306.cbf42b8480390ff8c8a9.js
evince/labextension/static/306.cbf42b8480390ff8c8a9.js.LICENSE.txt
evince/labextension/static/55.3ae3cfa37c26c601f9a2.js
evince/labextension/static/793.022f649f944c09ccac12.js
evince/labextension/static/793.0769750faca3f494eeb9.js
evince/labextension/static/793.0ad2db69dd7bb00580fd.js
evince/labextension/static/793.1866bdfbd1ab40a4e1d5.js
evince/labextension/static/793.198e5040c732c9846256.js
evince/labextension/static/793.21a2dda3d3d8caca0d4c.js
evince/labextension/static/793.25b62fdcf3af4e49e121.js
evince/labextension/static/793.2c10299dc902627e535d.js
evince/labextension/static/793.2cbaf6deba44ef7556f9.js
evince/labextension/static/793.363bf34768a5fc00e49a.js
evince/labextension/static/793.4265d305bbe76af34d1e.js
evince/labextension/static/793.445852e97b96a92fa76f.js
evince/labextension/static/793.4e0e4445529e7c50e933.js
evince/labextension/static/793.62bd00c9b1b15711be6e.js
evince/labextension/static/793.6ab9b9432cae19285788.js
evince/labextension/static/793.754410fd41078217ff72.js
evince/labextension/static/793.76e9582967a43bd1aec4.js
evince/labextension/static/793.76fb7b5b4f8c6115dabf.js
evince/labextension/static/793.7aa20d7bcf22d63c548c.js
evince/labextension/static/793.7e71ea8e0c835120c6c2.js
evince/labextension/static/793.7ebaa0b195868e666af5.js
evince/labextension/static/793.8181719390e77bfe1ca2.js
evince/labextension/static/793.8654541d99d6baaad99a.js
evince-0.57.0.dist-info/METADATA
evince-0.57.0.dist-info/WHEEL
evince-0.57.0.dist-info/top_level.txt
evince-0.57.0.dist-info/RECORD
